machines-0.0.1.data/data/my_data/data_file
machines-0.0.1.dist-info/DESCRIPTION.rst
machines-0.0.1.dist-info/METADATA
machines-0.0.1.dist-info/RECORD
machines-0.0.1.dist-info/WHEEL
machines-0.0.1.dist-info/entry_points.txt
machines-0.0.1.dist-info/metadata.json
machines-0.0.1.dist-info/top_level.txt
sample/__init__.py
sample/package_data.dat
